[null,{"name":"kakoa","permissions":"NONE","restriction":"1","actions":[{"gameName":"YONA_GAMING#5639 אם אתם רוצים להוסיף את הבוט לשרת שלכם תשלחו הצעת חברות","gameLink":"","name":"Set Bot Game"}]},{"name":"kick","permissions":"KICK_MEMBERS","restriction":"1","actions":[{"condition":"1","comparison":"0","value":"1","iftrue":"3","iftrueVal":"2","iffalse":"0","iffalseVal":"","name":"Check Parameters"},{"channel":"0","varName":"","message":"```\nPlease mention one user in order to kick them!\n!Kick [@user] [reason]\n```","storage":"0","varName2":"","name":"Send Message"},{"name":"End Action Sequence"},{"info":"1","infoIndex":"2","storage":"1","varName":"reason","name":"Store Command Params"},{"member":"0","varName":"","reason":"${tempVars(\"reason\") || \"\"}","name":"Kick Member"}]},{"name":"ban","permissions":"BAN_MEMBERS","restriction":"1","actions":[{"condition":"1","comparison":"0","value":"1","iftrue":"3","iftrueVal":"2","iffalse":"0","iffalseVal":"","name":"Check Parameters"},{"channel":"0","varName":"","message":"```\nPlease mention one user in order to ban them!\n!Ban [@user] [reason]\n```","storage":"0","varName2":"","name":"Send Message"},{"name":"End Action Sequence"},{"info":"1","infoIndex":"2","storage":"1","varName":"reason","name":"Store Command Params"},{"member":"0","varName":"","reason":"${tempVars(\"reason\") || \"\"}","name":"Ban Member"}]},{"name":"mute","permissions":"MUTE_MEMBERS","restriction":"1","actions":[{"condition":"1","comparison":"0","value":"1","iftrue":"3","iftrueVal":"2","iffalse":"0","iffalseVal":"","name":"Check Parameters"},{"channel":"0","varName":"","message":"```\nPlease mention one user in order to mute them!\n!Mute [@user]\n```","storage":"0","varName2":"","name":"Send Message"},{"name":"End Action Sequence"},{"member":"0","varName":"","mute":"0","name":"Set Member Mute"}]},{"name":"unmute","permissions":"MUTE_MEMBERS","restriction":"1","actions":[{"condition":"1","comparison":"0","value":"1","iftrue":"3","iftrueVal":"2","iffalse":"0","iffalseVal":"","name":"Check Parameters"},{"channel":"0","varName":"","message":"```\nPlease mention one user in order to unmute them!\n!Unmute [@user]\n```","storage":"0","varName2":"","name":"Send Message"},{"name":"End Action Sequence"},{"member":"0","varName":"","mute":"1","name":"Set Member Mute"}]},{"name":"DeleteChannel","permissions":"MANAGE_CHANNELS","restriction":"0","actions":[{"condition":"2","comparison":"0","value":"1","iftrue":"3","iftrueVal":"2","iffalse":"0","iffalseVal":"","name":"Check Parameters"},{"channel":"0","varName":"","message":"```\nPlease mention one channel in order to delete it!\n!DeleteChannel [#channel]\n```","storage":"0","varName2":"","name":"Send Message"},{"name":"End Action Sequence"},{"storage":"1","varName":"","name":"Delete Channel"}]},{"name":"DeleteRole","permissions":"MANAGE_ROLES","restriction":"0","actions":[{"condition":"3","comparison":"0","value":"1","iftrue":"3","iftrueVal":"2","iffalse":"0","iffalseVal":"","name":"Check Parameters"},{"channel":"0","varName":"","message":"```\nPlease mention one role in order to delete it!\n!DeleteRole [@role]\n```","storage":"0","varName2":"","name":"Send Message"},{"name":"End Action Sequence"},{"storage":"0","varName":"","name":"Delete Role"}]},{"name":"invite","permissions":"NONE","restriction":"1","actions":[{"info":"0","find":"434310233792184320","storage":"1","varName":"url","name":"Find Server"},{"channel":"0","varName":"","message":"${tempVars(\"url\")}","storage":"0","varName2":"","name":"Send Message"}]},{"name":"שלום","permissions":"NONE","restriction":"1","actions":[{"channel":"0","varName":"","message":"?שלום ממצב","storage":"0","varName2":"","name":"Send Message"}]},{"name":"deafen","permissions":"DEAFEN_MEMBERS","restriction":"1","actions":[{"member":"0","varName":"","deafen":"0","name":"Set Member Deafen"}]},{"name":"play","permissions":"NONE","restriction":"1","actions":[{"info":"1","infoIndex":"10","storage":"1","varName":"song","name":"Store Command Params"},{"channel":"0","varName":"","message":"Loadning song....","storage":"0","varName2":"","name":"Send Message"},{"video":"${tempVars(\"song\")}","key":"AIzaSyC_baWRhx0BNJxU5Yo0tSjgA9zKlhUyM6Q","info":"0","resultNo":"1","storage":"1","varName":"videourl","name":"YouTube Search"},{"name":"End Action Sequence"}]},{"name":"freefortnite","permissions":"MANAGE_EMOJIS","restriction":"1","actions":[{"channel":"0","varName":"","message":"i send you with....","storage":"0","varName2":"","name":"Send Message"},{"channel":"1","varName":"","message":"say thanks to YONA_GAMING https://web.h-gen.xyz/","storage":"0","varName2":"","name":"Send Message"}]},{"name":"freeminecraft","permissions":"MANAGE_EMOJIS","restriction":"1","actions":[{"channel":"0","varName":"","message":"i send you with....","storage":"0","varName2":"","name":"Send Message"},{"channel":"1","varName":"","message":"say thanks to YONA_GAMING https://web.h-gen.xyz/","storage":"0","varName2":"","name":"Send Message"}]},{"name":"freespofity","permissions":"MANAGE_EMOJIS","restriction":"1","actions":[{"channel":"0","varName":"","message":"i send you with....","storage":"0","varName2":"","name":"Send Message"},{"channel":"1","varName":"","message":"say thanks to YONA_GAMING https://web.h-gen.xyz/","storage":"0","varName2":"","name":"Send Message"}]},{"name":"freeuplay","permissions":"MANAGE_EMOJIS","restriction":"1","actions":[{"channel":"0","varName":"","message":"i send you with....","storage":"0","varName2":"","name":"Send Message"},{"channel":"1","varName":"","message":"say thanks to YONA_GAMING https://web.h-gen.xyz/","storage":"0","varName2":"","name":"Send Message"}]},{"name":"freeorigin","permissions":"MANAGE_EMOJIS","restriction":"1","actions":[{"channel":"0","varName":"","message":"i send you with....","storage":"0","varName2":"","name":"Send Message"},{"channel":"1","varName":"","message":"say thanks to YONA_GAMING https://web.h-gen.xyz/","storage":"0","varName2":"","name":"Send Message"}]},{"name":"freehulu","permissions":"MANAGE_EMOJIS","restriction":"1","actions":[{"channel":"0","varName":"","message":"i send you with....","storage":"0","varName2":"","name":"Send Message"},{"channel":"1","varName":"","message":"say thanks to YONA_GAMING https://web.h-gen.xyz/","storage":"0","varName2":"","name":"Send Message"}]},{"name":"freeeset","permissions":"MANAGE_EMOJIS","restriction":"1","actions":[{"channel":"0","varName":"","message":"i send you with....","storage":"0","varName2":"","name":"Send Message"},{"channel":"1","varName":"","message":"say thanks to YONA_GAMING https://web.h-gen.xyz/","storage":"0","varName2":"","name":"Send Message"}]},{"name":"freewish","permissions":"MANAGE_EMOJIS","restriction":"1","actions":[{"channel":"0","varName":"","message":"i send you with....","storage":"0","varName2":"","name":"Send Message"},{"channel":"1","varName":"","message":"say thanks to YONA_GAMING https://web.h-gen.xyz/","storage":"0","varName2":"","name":"Send Message"}]},{"name":"freepandora","permissions":"MANAGE_EMOJIS","restriction":"1","actions":[{"channel":"0","varName":"","message":"i send you with....","storage":"0","varName2":"","name":"Send Message"},{"channel":"1","varName":"","message":"say thanks to YONA_GAMING https://web.h-gen.xyz/","storage":"0","varName2":"","name":"Send Message"}]},{"name":"freeudemy","permissions":"MANAGE_EMOJIS","restriction":"1","actions":[{"channel":"0","varName":"","message":"i send you with....","storage":"0","varName2":"","name":"Send Message"},{"channel":"1","varName":"","message":"say thanks to YONA_GAMING https://web.h-gen.xyz/","storage":"0","varName2":"","name":"Send Message"}]},{"name":"freenordvpn","permissions":"MANAGE_EMOJIS","restriction":"1","actions":[{"channel":"0","varName":"","message":"i send you with....","storage":"0","varName2":"","name":"Send Message"},{"channel":"1","varName":"","message":"say thanks to YONA_GAMING https://web.h-gen.xyz/","storage":"0","varName2":"","name":"Send Message"}]}]